CHANGELOG
MANIFEST.in
README.md
setup.cfg
setup.py
test.py
Propel.egg-info/PKG-INFO
Propel.egg-info/SOURCES.txt
Propel.egg-info/dependency_links.txt
Propel.egg-info/entry_points.txt
Propel.egg-info/not-zip-safe
Propel.egg-info/pbr.json
Propel.egg-info/requires.txt
Propel.egg-info/top_level.txt
propel/__about__.py
propel/__about__.pyc
propel/__init__.py
propel/__init__.pyc